{
    "RECORDS": [
        {
            "id": "1",
            "attraction": "颐和园",
            "best_date": "6月-9月",
            "travel_preferences": "自然风光",
            "experience_pace": "悠闲放松"
        },
        {
            "id": "2",
            "attraction": "八达岭长城",
            "best_date": "5月-10月",
            "travel_preferences": "自然风光",
            "experience_pace": "混合"
        },
        {
            "id": "3",
            "attraction": "龙庆峡",
            "best_date": "5月-10月",
            "travel_preferences": "自然风光",
            "experience_pace": "混合"
        },
        {
            "id": "4",
            "attraction": "金海湖",
            "best_date": "5月-10月",
            "travel_preferences": "自然风光",
            "experience_pace": "悠闲放松"
        },
        {
            "id": "5",
            "attraction": "雁栖湖",
            "best_date": "5月-10月",
            "travel_preferences": "自然风光",
            "experience_pace": "悠闲放松"
        },
        {
            "id": "6",
            "attraction": "红螺寺",
            "best_date": "春秋季",
            "travel_preferences": "自然风光",
            "experience_pace": "混合"
        },
        {
            "id": "7",
            "attraction": "十渡风景区",
            "best_date": "5月-10月",
            "travel_preferences": "自然风光",
            "experience_pace": "混合"
        },
        {
            "id": "8",
            "attraction": "百里山水画廊",
            "best_date": "5月-10月",
            "travel_preferences": "自然风光",
            "experience_pace": "悠闲放松"
        },
        {
            "id": "9",
            "attraction": "云蒙山",
            "best_date": "4月-10月",
            "travel_preferences": "自然风光",
            "experience_pace": "混合"
        },
        {
            "id": "10",
            "attraction": "喇叭沟原始森林公园",
            "best_date": "5月-10月",
            "travel_preferences": "自然风光",
            "experience_pace": "混合"
        },
        {
            "id": "11",
            "attraction": "故宫博物院",
            "best_date": "4月-9月",
            "travel_preferences": "历史人文",
            "experience_pace": "悠闲放松"
        },
        {
            "id": "12",
            "attraction": "天坛公园",
            "best_date": "6月-9月",
            "travel_preferences": "历史人文",
            "experience_pace": "混合"
        },
        {
            "id": "13",
            "attraction": "明十三陵",
            "best_date": "4月-10月",
            "travel_preferences": "历史人文",
            "experience_pace": "混合"
        },
        {
            "id": "14",
            "attraction": "圆明园",
            "best_date": "7月-10月",
            "travel_preferences": "历史人文",
            "experience_pace": "混合"
        },
        {
            "id": "15",
            "attraction": "雍和宫",
            "best_date": "全年",
            "travel_preferences": "历史人文",
            "experience_pace": "混合"
        },
        {
            "id": "16",
            "attraction": "孔庙和国子监",
            "best_date": "全年",
            "travel_preferences": "历史人文",
            "experience_pace": "混合"
        },
        {
            "id": "17",
            "attraction": "周口店北京人遗址",
            "best_date": "全年",
            "travel_preferences": "历史人文",
            "experience_pace": "混合"
        },
        {
            "id": "18",
            "attraction": "云居寺",
            "best_date": "春秋季",
            "travel_preferences": "历史人文",
            "experience_pace": "混合"
        },
        {
            "id": "19",
            "attraction": "潭柘寺",
            "best_date": "春秋季",
            "travel_preferences": "历史人文",
            "experience_pace": "混合"
        },
        {
            "id": "20",
            "attraction": "戒台寺",
            "best_date": "春秋季",
            "travel_preferences": "历史人文",
            "experience_pace": "混合"
        },
        {
            "id": "21",
            "attraction": "前门大街",
            "best_date": "全年",
            "travel_preferences": "美食探店",
            "experience_pace": "悠闲放松"
        },
        {
            "id": "22",
            "attraction": "王府井小吃街",
            "best_date": "全年",
            "travel_preferences": "美食探店",
            "experience_pace": "悠闲放松"
        },
        {
            "id": "23",
            "attraction": "簋街",
            "best_date": "全年",
            "travel_preferences": "美食探店",
            "experience_pace": "悠闲放松"
        },
        {
            "id": "24",
            "attraction": "牛街",
            "best_date": "全年",
            "travel_preferences": "美食探店",
            "experience_pace": "悠闲放松"
        },
        {
            "id": "25",
            "attraction": "南锣鼓巷",
            "best_date": "8月-10月",
            "travel_preferences": "美食探店",
            "experience_pace": "悠闲放松"
        },
        {
            "id": "26",
            "attraction": "烟袋斜街",
            "best_date": "全年",
            "travel_preferences": "美食探店",
            "experience_pace": "悠闲放松"
        },
        {
            "id": "27",
            "attraction": "护国寺小吃街",
            "best_date": "全年",
            "travel_preferences": "美食探店",
            "experience_pace": "悠闲放松"
        },
        {
            "id": "28",
            "attraction": "方庄美食街",
            "best_date": "全年",
            "travel_preferences": "美食探店",
            "experience_pace": "悠闲放松"
        },
        {
            "id": "29",
            "attraction": "蓝色港湾",
            "best_date": "全年",
            "travel_preferences": "美食探店",
            "experience_pace": "悠闲放松"
        },
        {
            "id": "30",
            "attraction": "合生汇",
            "best_date": "全年",
            "travel_preferences": "美食探店",
            "experience_pace": "悠闲放松"
        },
        {
            "id": "31",
            "attraction": "北京动物园",
            "best_date": "4月-10月",
            "travel_preferences": "亲子乐园",
            "experience_pace": "混合"
        },
        {
            "id": "32",
            "attraction": "北京海洋馆",
            "best_date": "全年",
            "travel_preferences": "亲子乐园",
            "experience_pace": "混合"
        },
        {
            "id": "33",
            "attraction": "中国科技馆",
            "best_date": "全年",
            "travel_preferences": "亲子乐园",
            "experience_pace": "混合"
        },
        {
            "id": "34",
            "attraction": "北京天文馆",
            "best_date": "全年",
            "travel_preferences": "亲子乐园",
            "experience_pace": "混合"
        },
        {
            "id": "35",
            "attraction": "北京野生动物园",
            "best_date": "4月-10月",
            "travel_preferences": "亲子乐园",
            "experience_pace": "混合"
        },
        {
            "id": "36",
            "attraction": "北京环球度假区",
            "best_date": "春秋季",
            "travel_preferences": "亲子乐园",
            "experience_pace": "混合"
        },
        {
            "id": "37",
            "attraction": "北京欢乐谷",
            "best_date": "春秋季",
            "travel_preferences": "亲子乐园",
            "experience_pace": "暴走打卡"
        },
        {
            "id": "38",
            "attraction": "石景山游乐园",
            "best_date": "全年",
            "travel_preferences": "亲子乐园",
            "experience_pace": "混合"
        },
        {
            "id": "39",
            "attraction": "水立方嬉水乐园",
            "best_date": "全年",
            "travel_preferences": "亲子乐园",
            "experience_pace": "悠闲放松"
        },
        {
            "id": "40",
            "attraction": "中国儿童中心",
            "best_date": "全年",
            "travel_preferences": "亲子乐园",
            "experience_pace": "混合"
        },
        {
            "id": "41",
            "attraction": "十渡漂流",
            "best_date": "5月-10月",
            "travel_preferences": "冒险运动",
            "experience_pace": "暴走打卡"
        },
        {
            "id": "42",
            "attraction": "黄花城水长城",
            "best_date": "4月-10月",
            "travel_preferences": "冒险运动",
            "experience_pace": "混合"
        },
        {
            "id": "43",
            "attraction": "北京云佛山滑雪场",
            "best_date": "12月-次年2月",
            "travel_preferences": "冒险运动",
            "experience_pace": "暴走打卡"
        },
        {
            "id": "44",
            "attraction": "北京渔阳国际滑雪场",
            "best_date": "12月-次年2月",
            "travel_preferences": "冒险运动",
            "experience_pace": "暴走打卡"
        },
        {
            "id": "45",
            "attraction": "北京怀北国际滑雪场",
            "best_date": "12月-次年2月",
            "travel_preferences": "冒险运动",
            "experience_pace": "暴走打卡"
        },
        {
            "id": "46",
            "attraction": "北京军都山滑雪场",
            "best_date": "12月-次年2月",
            "travel_preferences": "冒险运动",
            "experience_pace": "暴走打卡"
        },
        {
            "id": "47",
            "attraction": "北京国际汽车露营公园",
            "best_date": "4月-10月",
            "travel_preferences": "冒险运动",
            "experience_pace": "混合"
        },
        {
            "id": "48",
            "attraction": "北京国际马术中心",
            "best_date": "全年",
            "travel_preferences": "冒险运动",
            "experience_pace": "混合"
        },
        {
            "id": "49",
            "attraction": "北京国际卡丁车场",
            "best_date": "全年",
            "travel_preferences": "冒险运动",
            "experience_pace": "混合"
        },
        {
            "id": "50",
            "attraction": "北京生存岛",
            "best_date": "全年",
            "travel_preferences": "冒险运动",
            "experience_pace": "混合"
        },
        {
            "id": "51",
            "attraction": "鸟巢（国家体育场）",
            "best_date": "全年",
            "travel_preferences": "摄影打卡",
            "experience_pace": "悠闲放松"
        },
        {
            "id": "52",
            "attraction": "水立方（国家游泳中心）",
            "best_date": "全年",
            "travel_preferences": "摄影打卡",
            "experience_pace": "悠闲放松"
        },
        {
            "id": "53",
            "attraction": "798艺术区",
            "best_date": "全年",
            "travel_preferences": "摄影打卡",
            "experience_pace": "悠闲放松"
        },
        {
            "id": "54",
            "attraction": "751艺术区",
            "best_date": "全年",
            "travel_preferences": "摄影打卡",
            "experience_pace": "悠闲放松"
        },
        {
            "id": "55",
            "attraction": "北京CBD",
            "best_date": "全年",
            "travel_preferences": "摄影打卡",
            "experience_pace": "悠闲放松"
        },
        {
            "id": "56",
            "attraction": "北京大观园",
            "best_date": "4月-10月",
            "travel_preferences": "摄影打卡",
            "experience_pace": "悠闲放松"
        },
        {
            "id": "57",
            "attraction": "北京明城墙遗址公园",
            "best_date": "全年",
            "travel_preferences": "摄影打卡",
            "experience_pace": "悠闲放松"
        },
        {
            "id": "58",
            "attraction": "北京古观象台",
            "best_date": "全年",
            "travel_preferences": "摄影打卡",
            "experience_pace": "悠闲放松"
        },
        {
            "id": "59",
            "attraction": "北京奥林匹克公园",
            "best_date": "全年",
            "travel_preferences": "摄影打卡",
            "experience_pace": "悠闲放松"
        },
        {
            "id": "60",
            "attraction": "北京世园会园区",
            "best_date": "全年",
            "travel_preferences": "摄影打卡",
            "experience_pace": "悠闲放松"
        },
        {
            "id": "61",
            "attraction": "王府井步行街",
            "best_date": "全年",
            "travel_preferences": "购物休闲",
            "experience_pace": "悠闲放松"
        },
        {
            "id": "62",
            "attraction": "北京环球城市大道",
            "best_date": "全年",
            "travel_preferences": "购物休闲",
            "experience_pace": "悠闲放松"
        },
        {
            "id": "63",
            "attraction": "国贸商城",
            "best_date": "全年",
            "travel_preferences": "购物休闲",
            "experience_pace": "悠闲放松"
        },
        {
            "id": "64",
            "attraction": "SKP",
            "best_date": "全年",
            "travel_preferences": "购物休闲",
            "experience_pace": "悠闲放松"
        },
        {
            "id": "65",
            "attraction": "三里屯太古里",
            "best_date": "全年",
            "travel_preferences": "购物休闲",
            "experience_pace": "悠闲放松"
        },
        {
            "id": "66",
            "attraction": "北京APM",
            "best_date": "全年",
            "travel_preferences": "购物休闲",
            "experience_pace": "悠闲放松"
        },
        {
            "id": "67",
            "attraction": "西单大悦城",
            "best_date": "全年",
            "travel_preferences": "购物休闲",
            "experience_pace": "悠闲放松"
        },
        {
            "id": "68",
            "attraction": "北京燕莎友谊商城",
            "best_date": "全年",
            "travel_preferences": "购物休闲",
            "experience_pace": "悠闲放松"
        },
        {
            "id": "69",
            "attraction": "北京金源燕莎MALL",
            "best_date": "全年",
            "travel_preferences": "购物休闲",
            "experience_pace": "悠闲放松"
        },
        {
            "id": "70",
            "attraction": "北京荟聚购物中心",
            "best_date": "全年",
            "travel_preferences": "购物休闲",
            "experience_pace": "悠闲放松"
        },
        {
            "id": "71",
            "attraction": "张裕爱斐堡酒庄",
            "best_date": "5月-10月",
            "travel_preferences": "小众体验",
            "experience_pace": "悠闲放松"
        },
        {
            "id": "72",
            "attraction": "北京张裕酒庄酒文化博物馆",
            "best_date": "5月-10月",
            "travel_preferences": "小众体验",
            "experience_pace": "悠闲放松"
        },
        {
            "id": "73",
            "attraction": "北京野鸭湖国家湿地公园",
            "best_date": "4月-10月",
            "travel_preferences": "小众体验",
            "experience_pace": "悠闲放松"
        },
        {
            "id": "74",
            "attraction": "北京南海子麋鹿苑",
            "best_date": "春秋季",
            "travel_preferences": "小众体验",
            "experience_pace": "悠闲放松"
        },
        {
            "id": "75",
            "attraction": "北京植物园",
            "best_date": "4月-10月",
            "travel_preferences": "小众体验",
            "experience_pace": "悠闲放松"
        },
        {
            "id": "76",
            "attraction": "北京世界花卉大观园",
            "best_date": "4月-10月",
            "travel_preferences": "小众体验",
            "experience_pace": "悠闲放松"
        },
        {
            "id": "77",
            "attraction": "北京国际鲜花港",
            "best_date": "4月-10月",
            "travel_preferences": "小众体验",
            "experience_pace": "悠闲放松"
        },
        {
            "id": "78",
            "attraction": "北京宋庆龄故居",
            "best_date": "全年",
            "travel_preferences": "小众体验",
            "experience_pace": "混合"
        },
        {
            "id": "79",
            "attraction": "北京老舍纪念馆",
            "best_date": "全年",
            "travel_preferences": "小众体验",
            "experience_pace": "混合"
        },
        {
            "id": "80",
            "attraction": "北京鲁迅博物馆",
            "best_date": "全年",
            "travel_preferences": "小众体验",
            "experience_pace": "混合"
        },
        {
            "id": "81",
            "attraction": "三元桥",
            "best_date": "全年",
            "travel_preferences": "购物休闲",
            "experience_pace": "混合"
        },
        {
            "id": "82",
            "attraction": "六里桥",
            "best_date": "全年",
            "travel_preferences": "购物休闲",
            "experience_pace": "混合"
        },
        {
            "id": "83",
            "attraction": "西直门站",
            "best_date": "全年",
            "travel_preferences": "购物休闲",
            "experience_pace": "混合"
        },
        {
            "id": "84",
            "attraction": "国贸地铁站",
            "best_date": "全年",
            "travel_preferences": "购物休闲",
            "experience_pace": "混合"
        }
    ]
}